save_tabs/__init__.py
save_tabs/advanced_cursor.py
save_tabs/browser_path.py
save_tabs/common.py
save_tabs/main.py
save_tabs/make_file.py
save_tabs/settings.py
save_tabs/window_macos.py
save_tabs/window_windows.py
save_tabs/scripts/applescript/focus_window.applescript
save_tabs/scripts/applescript/get_window_count.applescript
save_tabs/scripts/applescript/get_window_mode.applescript
save_tabs/scripts/applescript/get_window_urls.applescript
save_tabs/scripts/applescript/set_fullscreen.applescript
save_tabs-0.0.7.dist-info/METADATA
save_tabs-0.0.7.dist-info/WHEEL
save_tabs-0.0.7.dist-info/entry_points.txt
save_tabs-0.0.7.dist-info/licenses/LICENSE
save_tabs-0.0.7.dist-info/RECORD
